LICENSE
MANIFEST.in
README.rst
setup.py
game24/24gameconsole.py
game24/__init__.py
game24/calc.py
game24/game.py
game24.egg-info/PKG-INFO
game24.egg-info/SOURCES.txt
game24.egg-info/dependency_links.txt
game24.egg-info/entry_points.txt
game24.egg-info/top_level.txt